{
  "version": "1.0.0",
  "phase": 39,
  "probedAt": "2026-02-20T00:00:00Z",
  "vistaDistro": "WorldVistA EHR (Docker)",
  "vistaPort": 9430,
  "summary": {
    "totalRpcsProbed": 85,
    "liveEndpoints": 3,
    "pendingEndpoints": 3,
    "encounters": "live",
    "insurance": "live",
    "icdSearch": "live",
    "charges": "integration-pending",
    "claimsStatus": "integration-pending",
    "arStatus": "integration-pending"
  },
  "globals": {
    "IB_ACTION": {
      "global": "^IB(",
      "fileNumber": 350,
      "fileName": "INTEGRATED BILLING ACTION",
      "status": "empty",
      "count": 0,
      "note": "No billing actions in WorldVistA sandbox"
    },
    "IB_ACTION_TYPE": {
      "global": "^IBE(350.1,",
      "fileNumber": 350.1,
      "fileName": "IB ACTION TYPE",
      "status": "populated",
      "count": 122,
      "note": "IB action type definitions present -- reference data only"
    },
    "CLAIMS_TRACKING": {
      "global": "^DGCR(399,",
      "fileNumber": 399,
      "fileName": "BILL/CLAIMS",
      "status": "empty",
      "count": 0,
      "note": "No claims in WorldVistA sandbox. Target for production IB integration."
    },
    "AR_TRANSACTION": {
      "global": "^PRCA(430,",
      "fileNumber": 430,
      "fileName": "ACCOUNTS RECEIVABLE",
      "status": "empty",
      "count": 0,
      "note": "No AR transactions in sandbox"
    },
    "AR_PAYMENT": {
      "global": "^PRCA(433,",
      "fileNumber": 433,
      "fileName": "AR TRANSACTION",
      "status": "populated",
      "count": 2,
      "note": "2 payment records exist (likely seed data)"
    },
    "VISIT": {
      "global": "^AUPNVSIT(",
      "fileNumber": 9000010,
      "fileName": "VISIT",
      "status": "populated",
      "count": 68,
      "note": "68 PCE visits with dates/locations. Fully queryable."
    },
    "V_CPT": {
      "global": "^AUPNVCPT(",
      "fileNumber": "9000010.18",
      "fileName": "V CPT",
      "status": "populated",
      "count": 32,
      "note": "32 procedure codes linked to visits"
    },
    "V_POV": {
      "global": "^AUPNVPOV(",
      "fileNumber": "9000010.07",
      "fileName": "V POV",
      "status": "populated",
      "count": 28,
      "note": "28 diagnoses (purpose of visit) linked to visits"
    },
    "HOSPITAL_LOCATION": {
      "global": "^SC(",
      "fileNumber": 44,
      "fileName": "HOSPITAL LOCATION",
      "status": "populated",
      "count": 10,
      "note": "10 locations including DR OFFICE (type C), LAB (type C)"
    },
    "INSURANCE_COMPANY": {
      "global": "^DIC(36,",
      "fileNumber": 36,
      "fileName": "INSURANCE COMPANY",
      "status": "populated",
      "count": 2,
      "note": "2 insurance companies in sandbox"
    },
    "PATIENT_INSURANCE": {
      "global": "^DPT(N,.312)",
      "fileNumber": "2.312",
      "fileName": "PATIENT - INSURANCE TYPE (sub-file)",
      "status": "partial",
      "note": "Patient 3 has partial insurance data. Not all patients have coverage."
    }
  },
  "rpcs": {
    "encounter_read": {
      "status": "live",
      "rpcs": [
        { "name": "ORWPCE GET VISIT", "ien": 683, "purpose": "Get encounter data for a visit", "sandbox": "available" },
        { "name": "ORWPCE DIAG", "ien": 320, "purpose": "Get diagnoses for encounter", "sandbox": "available" },
        { "name": "ORWPCE PROC", "ien": 321, "purpose": "Get procedures for encounter", "sandbox": "available" },
        { "name": "ORWPCE VISIT", "ien": 322, "purpose": "Get visit details", "sandbox": "available" },
        { "name": "ORWPCE PCE4NOTE", "ien": 329, "purpose": "Get PCE data linked to a note", "sandbox": "available" },
        { "name": "ORWPCE HASVISIT", "ien": 739, "purpose": "Check if note has linked visit", "sandbox": "available" },
        { "name": "ORWPCE GETSVC", "ien": 831, "purpose": "Get service connected conditions", "sandbox": "available" }
      ]
    },
    "encounter_write": {
      "status": "live",
      "rpcs": [
        { "name": "ORWPCE SAVE", "ien": 336, "purpose": "Save encounter data (write-back)", "sandbox": "available" }
      ]
    },
    "encounter_lookup": {
      "status": "live",
      "rpcs": [
        { "name": "ORWPCE4 LEX", "ien": 2930, "purpose": "ICD-10/lexicon search", "sandbox": "available" },
        { "name": "ORWPCE LEX", "ien": 340, "purpose": "Lexicon search (older)", "sandbox": "available" },
        { "name": "ORWPCE LEXCODE", "ien": 341, "purpose": "Get code for lexicon entry", "sandbox": "available" },
        { "name": "ORWPCE ACTIVE CODE", "ien": 1555, "purpose": "Check if ICD code is active", "sandbox": "available" },
        { "name": "ORWPCE ICDVER", "ien": 2924, "purpose": "Get ICD version date", "sandbox": "available" },
        { "name": "ORWPCE I10IMPDT", "ien": 2947, "purpose": "ICD-10 implementation date", "sandbox": "available" },
        { "name": "ORWPCE GET DX TEXT", "ien": 2837, "purpose": "Get diagnosis display text", "sandbox": "available" }
      ]
    },
    "encounter_clinical": {
      "status": "live",
      "rpcs": [
        { "name": "ORWPCE IMM", "ien": 447, "purpose": "Immunizations for encounter", "sandbox": "available" },
        { "name": "ORWPCE SK", "ien": 448, "purpose": "Skin tests for encounter", "sandbox": "available" },
        { "name": "ORWPCE PED", "ien": 449, "purpose": "Patient education for encounter", "sandbox": "available" },
        { "name": "ORWPCE HF", "ien": 450, "purpose": "Health factors for encounter", "sandbox": "available" },
        { "name": "ORWPCE TRT", "ien": 451, "purpose": "Treatments for encounter", "sandbox": "available" },
        { "name": "ORWPCE XAM", "ien": 452, "purpose": "Exams for encounter", "sandbox": "available" }
      ]
    },
    "ibd_forms": {
      "status": "live",
      "note": "IBD (Integrated Billing Data) form RPCs -- capture billing data at encounter",
      "rpcs": [
        { "name": "IBD EXPAND FORMID", "ien": 70, "purpose": "Expand billing form ID", "sandbox": "available" },
        { "name": "IBD GET FORMSPEC", "ien": 71, "purpose": "Get billing form specification", "sandbox": "available" },
        { "name": "IBD GET INPUT OBJECT BY CLINIC", "ien": 72, "purpose": "Get billing input objects for clinic", "sandbox": "available" },
        { "name": "IBD GET ALL PCE DATA", "ien": 113, "purpose": "Get all PCE data for billing", "sandbox": "available" },
        { "name": "IBD VALIDATE USER", "ien": 76, "purpose": "Validate user for billing", "sandbox": "available" }
      ]
    },
    "insurance_query": {
      "status": "live",
      "rpcs": [
        { "name": "IBCN INSURANCE QUERY", "ien": 1497, "purpose": "Query patient insurance coverage", "sandbox": "available" },
        { "name": "IBCN INSURANCE QUERY TASK", "ien": 1498, "purpose": "Tasked insurance query", "sandbox": "available" }
      ]
    },
    "pharmacy_billing": {
      "status": "live",
      "rpcs": [
        { "name": "IBARXM QUERY ONLY", "ien": 769, "purpose": "Pharmacy billing query", "sandbox": "available" },
        { "name": "IBARXM TRANS DATA", "ien": 770, "purpose": "Pharmacy transaction data", "sandbox": "available" },
        { "name": "IBARXM TRANS BILL", "ien": 1117, "purpose": "Pharmacy billing transaction", "sandbox": "available" }
      ]
    },
    "ib_means_test": {
      "status": "live",
      "rpcs": [
        { "name": "IBO MT LTC COPAY QUERY", "ien": 1320, "purpose": "Means test / LTC copay query", "sandbox": "available" },
        { "name": "DGBT CLAIM DEDUCTIBLE PAID", "ien": 2911, "purpose": "Claim deductible status", "sandbox": "available" }
      ]
    },
    "scheduling": {
      "status": "live",
      "rpcs": [
        { "name": "SD W/L RETRIVE FULL DATA", "ien": 1293, "purpose": "Wait list full data", "sandbox": "available" },
        { "name": "SD W/L RETRIVE BRIEF", "ien": 1295, "purpose": "Wait list brief", "sandbox": "available" },
        { "name": "SD W/L RETRIVE HOSP LOC(#44)", "ien": 1300, "purpose": "Wait list by location", "sandbox": "available" }
      ]
    },
    "ib_claims_processing": {
      "status": "integration-pending",
      "note": "Claims processing RPCs exist but ^DGCR(399) is empty. Real IB claims require IB GENERATE CLAIM/IB EXTRACT BILL workflows.",
      "targetFiles": ["399 (BILL/CLAIMS)", "350 (IB ACTION)"],
      "targetRoutines": ["IBCF", "IBCE", "IBJP"],
      "rpcs": []
    },
    "ar_management": {
      "status": "integration-pending",
      "note": "AR Transaction file (430) is empty. Requires IB -> AR billing pipeline.",
      "targetFiles": ["430 (ACCOUNTS RECEIVABLE)", "433 (AR TRANSACTION)"],
      "targetRoutines": ["PRCAFN", "PRCASER", "PRCATR"],
      "rpcs": []
    }
  },
  "routines": {
    "IBRFN": { "status": "present", "purpose": "IB utility functions" },
    "IBCNSP": { "status": "present", "purpose": "IB insurance company search" },
    "IBCNS": { "status": "present", "purpose": "IB insurance company" },
    "PRCAFN": { "status": "present", "purpose": "AR utility functions" },
    "PRCASER": { "status": "present", "purpose": "AR service functions" },
    "ORWPCE": { "status": "present", "purpose": "PCE encounter form driver" }
  },
  "endpoints": [
    {
      "path": "/vista/rcm/encounters",
      "method": "GET",
      "status": "live",
      "params": "dfn (required)",
      "rpcsUsed": ["ORWPCE VISIT", "ORWPCE PCE4NOTE"],
      "vistaFiles": ["9000010 (VISIT)", "9000010.18 (V CPT)", "9000010.07 (V POV)"],
      "description": "Patient encounter history from PCE"
    },
    {
      "path": "/vista/rcm/insurance",
      "method": "GET",
      "status": "live",
      "params": "dfn (required)",
      "rpcsUsed": ["IBCN INSURANCE QUERY"],
      "vistaFiles": ["36 (INSURANCE COMPANY)", "2.312 (PATIENT INSURANCE)"],
      "description": "Patient insurance coverage from VistA"
    },
    {
      "path": "/vista/rcm/icd-search",
      "method": "GET",
      "status": "live",
      "params": "text (required)",
      "rpcsUsed": ["ORWPCE4 LEX"],
      "vistaFiles": [],
      "description": "ICD-10 diagnosis code search"
    },
    {
      "path": "/vista/rcm/charges",
      "method": "GET",
      "status": "integration-pending",
      "params": "dfn (required)",
      "rpcsUsed": [],
      "vistaFiles": ["350 (IB ACTION)"],
      "targetRoutines": ["IBCF", "IBCE"],
      "description": "IB charges -- sandbox has no charge data. Requires IB ACTION entries.",
      "migrationPath": "When IB billing is configured, call IB RPCs to read ^IB(350) actions for patient"
    },
    {
      "path": "/vista/rcm/claims-status",
      "method": "GET",
      "status": "integration-pending",
      "params": "dfn (required)",
      "rpcsUsed": [],
      "vistaFiles": ["399 (BILL/CLAIMS)"],
      "targetRoutines": ["IBCF", "IBJP"],
      "description": "Claims tracking -- sandbox has no claims data. Requires ^DGCR(399) population.",
      "migrationPath": "When IB claims are generated, read ^DGCR(399) via FileMan or custom RPC"
    },
    {
      "path": "/vista/rcm/ar-status",
      "method": "GET",
      "status": "integration-pending",
      "params": "dfn (required)",
      "rpcsUsed": [],
      "vistaFiles": ["430 (ACCOUNTS RECEIVABLE)", "433 (AR TRANSACTION)"],
      "targetRoutines": ["PRCAFN", "PRCASER"],
      "description": "AR balance -- sandbox has no AR data. Requires IB->AR pipeline.",
      "migrationPath": "When AR is populated, use PRCA RPCs or FileMan to query ^PRCA(430) by patient"
    }
  ]
}
