{
  "fileNumber": 661.41,
  "fileName": "HCPCS INVENTORY ORDER AND REORDER",
  "globalRoot": "661.41",
  "globalReference": "^RMPR(661.41,",
  "ddAccess": "N",
  "securityAudit": "audited",
  "fields": [
    {
      "fieldNumber": .01,
      "fieldName": "DATE ORDERED",
      "dataType": "DATE",
      "rawType": "RD",
      "required": true,
      "helpText": "This is the date when an item is ordered. ",
      "fieldNumber_": .01
    },
    {
      "fieldNumber": 1,
      "fieldName": "HCPCS ITEM",
      "dataType": "NUMERIC",
      "rawType": "NJ4,0",
      "length": 4,
      "required": false,
      "helpText": "This is the Item number of an HCPCS Item. ",
      "fieldNumber_": 1
    },
    {
      "fieldNumber": 2,
      "fieldName": "STATION",
      "dataType": "POINTER",
      "rawType": "P4'",
      "required": false,
      "pointerTo": 4,
      "helpText": "This is the staton where an HCPCS belong to. ",
      "fieldNumber_": 2
    },
    {
      "fieldNumber": 4,
      "fieldName": "VENDOR",
      "dataType": "POINTER",
      "rawType": "P440'",
      "required": false,
      "pointerTo": 440,
      "helpText": "A pointer to Vendor file in IFCAP. ",
      "fieldNumber_": 4
    },
    {
      "fieldNumber": 5,
      "fieldName": "HCPCS",
      "dataType": "FREE-TEXT",
      "rawType": "F",
      "required": false,
      "helpText": "This is the PSAS HCPCS as entered in 01 field of file # 661.1. ",
      "fieldNumber_": 5
    },
    {
      "fieldNumber": 6,
      "fieldName": "DATE RECIEVED",
      "dataType": "DATE",
      "rawType": "D",
      "required": false,
      "helpText": "The date date when an Item is recieved. ",
      "fieldNumber_": 6
    },
    {
      "fieldNumber": 7,
      "fieldName": "QTY ORDERED",
      "dataType": "NUMERIC",
      "rawType": "NJ5,0",
      "length": 5,
      "required": false,
      "helpText": "A number that signifies the quantity being being ordered. ",
      "fieldNumber_": 7
    },
    {
      "fieldNumber": 8,
      "fieldName": "QTY RECIEVED",
      "dataType": "NUMERIC",
      "rawType": "NJ5,0",
      "length": 5,
      "required": false,
      "helpText": "A number that signifies the quatity recieved. ",
      "fieldNumber_": 8
    },
    {
      "fieldNumber": 9,
      "fieldName": "COMMENTS",
      "dataType": "FREE-TEXT",
      "rawType": "F",
      "required": false,
      "helpText": "This is a free text field that can be used for comments or any description of an item being ordered. ",
      "fieldNumber_": 9
    },
    {
      "fieldNumber": 10,
      "fieldName": "STATUS",
      "dataType": "SET",
      "rawType": "S",
      "required": false,
      "setOfCodes": "C:CANCELLED;O:OPEN;R:RECEIVED;",
      "fieldNumber_": 10
    }
  ],
  "fieldCount": 10,
  "crossReferences": [
    {"name": "B", "field": },
    {"name": "661.41", "field": .01, "type": "regular"}
  ],
  "identifiers": [

  ]
}
