{
  "fileNumber": 50,
  "fileName": "DRUG",
  "globalRoot": "50I",
  "globalReference": "^PSDRUG(",
  "ddAccess": "N",
  "securityAudit": "",
  "fields": [
    {
      "fieldNumber": .001,
      "fieldName": "NUMBER",
      "dataType": "NUMERIC",
      "rawType": "NJ5,0",
      "length": 5,
      "required": false,
      "helpText": "This field contains the internal record number of the drug.   ",
      "fieldNumber_": .001
    },
    {
      "fieldNumber": .01,
      "fieldName": "GENERIC NAME",
      "dataType": "FREE-TEXT",
      "rawType": "RFXa",
      "required": true,
      "helpText": "This is the generic name of the drug. In addition, if this entry is marked for CMOP transmission, the generic name cannot be edited unless it is UNmarked for CMOP transmission first. ",
      "fieldNumber_": .01
    },
    {
      "fieldNumber": 1,
      "fieldName": "AHFS NUMBER",
      "dataType": "COMPUTED",
      "rawType": "CJ8X",
      "length": 8X,
      "required": false,
      "fieldNumber_": 1
    },
    {
      "fieldNumber": 2,
      "fieldName": "VA CLASSIFICATION",
      "dataType": "FREE-TEXT",
      "rawType": "FX",
      "required": false,
      "helpText": "  This is the VA classification for this drug. ",
      "fieldNumber_": 2
    },
    {
      "fieldNumber": 2.1,
      "fieldName": "PHARMACY ORDERABLE ITEM",
      "dataType": "POINTER",
      "rawType": "P50.7X",
      "required": false,
      "pointerTo": 50.7,
      "helpText": "Name used by ORDER ENTRY/RESULTS REPORTING. ",
      "fieldNumber_": 2.1
    },
    {
      "fieldNumber": 3,
      "fieldName": "DEA, SPECIAL HDLG",
      "dataType": "FREE-TEXT",
      "rawType": "FX",
      "required": false,
      "helpText": "This field is used to show the DEA Special Handling . ",
      "fieldNumber_": 3
    },
    {
      "fieldNumber": 4,
      "fieldName": "MAXIMUM DOSE PER DAY",
      "dataType": "NUMERIC",
      "rawType": "NJ5,1",
      "length": 5,
      "required": false,
      "helpText": "This field is used as a standard maximum dosage. ",
      "fieldNumber_": 4
    },
    {
      "fieldNumber": 5,
      "fieldName": "STANDARD SIG",
      "dataType": "FREE-TEXT",
      "rawType": "FX",
      "required": false,
      "helpText": "This field is used as a standard default for medication instructions. ",
      "fieldNumber_": 5
    },
    {
      "fieldNumber": 6,
      "fieldName": "FSN",
      "dataType": "FREE-TEXT",
      "rawType": "F",
      "required": false,
      "helpText": "  This is the federal stock number of this drug. ",
      "fieldNumber_": 6
    },
    {
      "fieldNumber": 8,
      "fieldName": "WARNING LABEL",
      "dataType": "FREE-TEXT",
      "rawType": "FX",
      "required": false,
      "helpText": "This field is used to indicate if a warning should be printed with the selection of this drug. ",
      "fieldNumber_": 8
    },
    {
      "fieldNumber": 8.1,
      "fieldName": "NEW WARNING LABEL LIST",
      "dataType": "FREE-TEXT",
      "rawType": "FX",
      "required": false,
      "helpText": "Enter a comma-delimited list of warning numbers from old and new warning  files, following new file entries with an \"N\". ",
      "fieldNumber_": 8.1
    },
    {
      "fieldNumber": 8.2,
      "fieldName": "GENDER SPECIFIC LBLS ON ALL RX",
      "dataType": "SET",
      "rawType": "S",
      "required": false,
      "setOfCodes": "Y:YES;N:NO;",
      "helpText": "If this field contains \"N\", warning labels that are marked with a SPECIFIC TO GENDER value of \"M\" for Male or \"F\" for Female will only print for this drug when the patient is that specific gender. If this field is null or  contains a \"Y\", then the warning will print for both genders. ",
      "fieldNumber_": 8.2
    },
    {
      "fieldNumber": 9,
      "fieldName": "SYNONYM",
      "dataType": "SUBFILE",
      "rawType": "50.1A",
      "required": false,
      "helpText": "This multiple contains the Synonym, NDC Code, Intended Use, VSN, Order  Unit, Price per Order Unit, Dispense Units per Order Unit, Price per  Dispense Unit, and Vendor fields. It is used for a quick code for look  ups or to locate NDCs to increment the drug's inventory when orders  are received. ",
      "isMultiple": true,
      "subFileNumber": 50.1,
      "fieldNumber_": 9
    },
    {
      "fieldNumber": 11,
      "fieldName": "REORDER LEVEL",
      "dataType": "NUMERIC",
      "rawType": "NJ4,0",
      "length": 4,
      "required": false,
      "helpText": "This field is used to indicate the reorder level for this drug. ",
      "fieldNumber_": 11
    },
    {
      "fieldNumber": 12,
      "fieldName": "ORDER UNIT",
      "dataType": "POINTER",
      "rawType": "P51.5'",
      "required": false,
      "pointerTo": 51.5,
      "helpText": "  This is the order unit for this drug. ",
      "fieldNumber_": 12
    },
    {
      "fieldNumber": 13,
      "fieldName": "PRICE PER ORDER UNIT",
      "dataType": "NUMERIC",
      "rawType": "NJ7,2X",
      "length": 7,
      "required": false,
      "helpText": "  This is the price per order unit for this drug. ",
      "fieldNumber_": 13
    },
    {
      "fieldNumber": 14,
      "fieldName": "NORMAL AMOUNT TO ORDER",
      "dataType": "NUMERIC",
      "rawType": "NJ3,0",
      "length": 3,
      "required": false,
      "helpText": "  This is the normal amount to order for this drug. ",
      "fieldNumber_": 14
    },
    {
      "fieldNumber": 14.5,
      "fieldName": "DISPENSE UNIT",
      "dataType": "FREE-TEXT",
      "rawType": "Fa",
      "required": false,
      "helpText": "  This is the dispense unit for this drug. ",
      "fieldNumber_": 14.5
    },
    {
      "fieldNumber": 15,
      "fieldName": "DISPENSE UNITS PER ORDER UNIT",
      "dataType": "NUMERIC",
      "rawType": "NJ10,4",
      "length": 10,
      "required": false,
      "helpText": "  This is the dispense units per order unit for this drug. ",
      "fieldNumber_": 15
    },
    {
      "fieldNumber": 16,
      "fieldName": "PRICE PER DISPENSE UNIT",
      "dataType": "NUMERIC",
      "rawType": "NJ11,4",
      "length": 11,
      "required": false,
      "helpText": "  This is the price per dispense unit for this drug. ",
      "fieldNumber_": 16
    },
    {
      "fieldNumber": 17,
      "fieldName": "SOURCE OF SUPPLY",
      "dataType": "FREE-TEXT",
      "rawType": "F",
      "required": false,
      "helpText": "This field is used to indicate the source of the supply for this medication/ supply. ",
      "fieldNumber_": 17
    },
    {
      "fieldNumber": 17.1,
      "fieldName": "EXPIRATION DATE",
      "dataType": "DATE",
      "rawType": "D",
      "required": false,
      "helpText": "This field is used to show the expiration date of the current supply of available drugs. ",
      "fieldNumber_": 17.1
    },
    {
      "fieldNumber": 17.2,
      "fieldName": "LAB TEST MONITOR",
      "dataType": "POINTER",
      "rawType": "P60'X",
      "required": false,
      "pointerTo": 60,
      "helpText": "This is the lab test results which should be checked before this drug  is dispensed. ",
      "fieldNumber_": 17.2
    },
    {
      "fieldNumber": 17.3,
      "fieldName": "MONITOR MAX DAYS",
      "dataType": "NUMERIC",
      "rawType": "NJ3,0X",
      "length": 3,
      "required": false,
      "helpText": "This is the number of days during which the results of the lab test are of interest when dispensing this drug. ",
      "fieldNumber_": 17.3
    },
    {
      "fieldNumber": 17.4,
      "fieldName": "SPECIMEN TYPE",
      "dataType": "POINTER",
      "rawType": "P61'X",
      "required": false,
      "pointerTo": 61,
      "helpText": "This is the specimen type on which the lab test should be run. ",
      "fieldNumber_": 17.4
    },
    {
      "fieldNumber": 17.5,
      "fieldName": "MONITOR ROUTINE",
      "dataType": "FREE-TEXT",
      "rawType": "F",
      "required": false,
      "helpText": "This is the name of the routine which is called to do all necessary checking on lab test results before dispensing this drug. ",
      "fieldNumber_": 17.5
    },
    {
      "fieldNumber": 17.6,
      "fieldName": "LAB MONITOR MARK",
      "dataType": "SET",
      "rawType": "S",
      "required": false,
      "setOfCodes": "1:YES;",
      "helpText": "This field is set to \"1\" if the drug is marked for Lab Monitor purposes. ",
      "fieldNumber_": 17.6
    },
    {
      "fieldNumber": 17.7,
      "fieldName": "CLOZAPINE LAB TEST",
      "dataType": "POINTER",
      "rawType": "50.02P",
      "required": false,
      "fieldNumber_": 17.7
    },
    {
      "fieldNumber": 18,
      "fieldName": "INV ORDER UNITS",
      "dataType": "COMPUTED",
      "rawType": "CJ8,2",
      "length": 8,
      "required": false,
      "helpText": "  This is the inventory order units for this drug. ",
      "fieldNumber_": 18
    },
    {
      "fieldNumber": 20,
      "fieldName": "NATIONAL DRUG FILE ENTRY",
      "dataType": "POINTER",
      "rawType": "P50.6",
      "required": false,
      "pointerTo": 50.6,
      "helpText": "This is the pointer to the National Drug file (^PSNDF). ",
      "fieldNumber_": 20
    },
    {
      "fieldNumber": 21,
      "fieldName": "VA PRODUCT NAME",
      "dataType": "FREE-TEXT",
      "rawType": "F",
      "required": false,
      "helpText": "This is the VA Product Name matched to in the National Drug file. ",
      "fieldNumber_": 21
    },
    {
      "fieldNumber": 22,
      "fieldName": "PSNDF VA PRODUCT NAME ENTRY",
      "dataType": "POINTER",
      "rawType": "P50.68O",
      "required": false,
      "pointerTo": 50.68,
      "helpText": "This is the pointer to the VA Product file in the National Drug File package. ",
      "fieldNumber_": 22
    },
    {
      "fieldNumber": 23,
      "fieldName": "PACKAGE SIZE",
      "dataType": "POINTER",
      "rawType": "P50.609",
      "required": false,
      "pointerTo": 50.609,
      "helpText": "This is the pointer to the Package Size file. ",
      "fieldNumber_": 23
    },
    {
      "fieldNumber": 24,
      "fieldName": "PACKAGE TYPE",
      "dataType": "POINTER",
      "rawType": "P50.608",
      "required": false,
      "pointerTo": 50.608,
      "helpText": "This is the pointer to the Package Type file. ",
      "fieldNumber_": 24
    },
    {
      "fieldNumber": 25,
      "fieldName": "NATIONAL DRUG CLASS",
      "dataType": "POINTER",
      "rawType": "P50.605'",
      "required": false,
      "pointerTo": 50.605,
      "helpText": "This is the pointer to the VA Drug Class file. ",
      "fieldNumber_": 25
    },
    {
      "fieldNumber": 26,
      "fieldName": "VA DRUG CLASS CODE",
      "dataType": "COMPUTED",
      "rawType": "CJ40",
      "length": 40,
      "required": false,
      "helpText": "This is the VA Drug Class Code along with the description of that class. ",
      "fieldNumber_": 26
    },
    {
      "fieldNumber": 27,
      "fieldName": "CMOP ID",
      "dataType": "FREE-TEXT",
      "rawType": "F",
      "required": false,
      "helpText": "This field contains the VA CMOP National Identifier from NDF. ",
      "fieldNumber_": 27
    },
    {
      "fieldNumber": 28,
      "fieldName": "OP EXTERNAL DISPENSE",
      "dataType": "SET",
      "rawType": "S",
      "required": false,
      "setOfCodes": "1:YES;0:NO;",
      "helpText": "Indicates if this drug may be dispensed to an external interface dispensing machine. ",
      "fieldNumber_": 28
    },
    {
      "fieldNumber": 29,
      "fieldName": "NATIONAL FORMULARY INDICATOR",
      "dataType": "SET",
      "rawType": "S",
      "required": false,
      "setOfCodes": "1:YES;0:NO;",
      "helpText": "This field will be used to determine whether this drug is on the National Formulary. Data will be maintained at the national level. This field will be populated during the NDF matching process. The data cannot be edited at the local level. ",
      "fieldNumber_": 29
    },
    {
      "fieldNumber": 31,
      "fieldName": "NDC",
      "dataType": "FREE-TEXT",
      "rawType": "FX",
      "required": false,
      "helpText": "This is the National Drug Code for this drug. ",
      "fieldNumber_": 31
    },
    {
      "fieldNumber": 32,
      "fieldName": "NDC BY OUTPATIENT SITE",
      "dataType": "POINTER",
      "rawType": "50.032P",
      "required": false,
      "fieldNumber_": 32
    },
    {
      "fieldNumber": 37,
      "fieldName": "DRUG TEXT ENTRY",
      "dataType": "POINTER",
      "rawType": "50.037P",
      "required": false,
      "fieldNumber_": 37
    },
    {
      "fieldNumber": 40,
      "fieldName": "ACTION PROFILE MESSAGE (OP)",
      "dataType": "FREE-TEXT",
      "rawType": "F",
      "required": false,
      "helpText": "This message will be printed on the Outpatient action profile along with the other information for each prescription for this drug. ",
      "fieldNumber_": 40
    },
    {
      "fieldNumber": 50,
      "fieldName": "CURRENT INVENTORY",
      "dataType": "NUMERIC",
      "rawType": "NJ8,0X",
      "length": 8,
      "required": false,
      "helpText": "This field contains the current number of the drug in stock. ",
      "fieldNumber_": 50
    },
    {
      "fieldNumber": 50.095,
      "fieldName": "DT/TM DISP UNIT PRICE CHANGED",
      "dataType": "DATE",
      "rawType": "50.095DA",
      "required": false,
      "helpText": "This field tracks the Date and Time whenever the PRICE PER DISPENSE UNIT (#16) field is changed.  It is set using a trigger cross-reference on the PRICE PER DISPENSE UNIT (#16) field. ",
      "isMultiple": true,
      "subFileNumber": 50.095,
      "fieldNumber_": 50.095
    },
    {
      "fieldNumber": 51,
      "fieldName": "LOCAL NON-FORMULARY",
      "dataType": "SET",
      "rawType": "SX",
      "required": false,
      "setOfCodes": "1:N/F;",
      "helpText": "  This is used to designate the drug as non-formulary. ",
      "fieldNumber_": 51
    },
    {
      "fieldNumber": 52,
      "fieldName": "VISN NON-FORMULARY",
      "dataType": "SET",
      "rawType": "S",
      "required": false,
      "setOfCodes": "1:V-N/F;",
      "helpText": "This field will designate a drug that is not on the VISN Formulary. ",
      "fieldNumber_": 52
    },
    {
      "fieldNumber": 62.01,
      "fieldName": "DAY (nD) or DOSE (nL) LIMIT",
      "dataType": "FREE-TEXT",
      "rawType": "FX",
      "required": false,
      "helpText": "  This is mainly for NARCOTICS and ANTIBIOTICS.  If a number is found here when this medication is selected for a UNIT DOSE order, that number will be used to calculate the DEFAULT value for the STOP DATE/TIME prompt in the entry of that order.  If the number entered is followed by a \"D\", that number of days will be added to the START DATE.  If the number is followed by an \"L\", that number will be used to calculate the DOSE LIMIT. ",
      "fieldNumber_": 62.01
    },
    {
      "fieldNumber": 62.02,
      "fieldName": "UNIT DOSE MED ROUTE",
      "dataType": "POINTER",
      "rawType": "*P51.2'",
      "required": false,
      "pointerTo": 51.2,
      "helpText": "  If data is found here when this medication is selected for a UNIT DOSE order, that data will be used as the DEFAULT value for the MED ROUTE prompt in ORDER ENTRY.  Please note that ORAL is not selectable as a MED ROUTE here, since it is the standard default value in order entry.   here, since it is the standard default value in order entry. ",
      "fieldNumber_": 62.02
    },
    {
      "fieldNumber": 62.03,
      "fieldName": "UNIT DOSE SCHEDULE TYPE",
      "dataType": "SET",
      "rawType": "S",
      "required": false,
      "setOfCodes": "OC:ON CALL;O:ONE TIME;P:PRN;R:FILL on REQUEST;",
      "helpText": "  If data is found here when this medication is selected for a UNIT DOSE  order, that data will be used as the DEFAULT value for the SCHEDULE TYPE  prompt in ORDER ENTRY.   Please note that you will NOT find CONTINUOUS as a SCHEDULE TYPE here, since it is the standard default in order entry. ",
      "fieldNumber_": 62.03
    },
    {
      "fieldNumber": 62.04,
      "fieldName": "UNIT DOSE SCHEDULE",
      "dataType": "FREE-TEXT",
      "rawType": "FX",
      "required": false,
      "helpText": "  If a schedule is found here when this medication is selected for a UNIT DOSE order, that schedule will be used as a default value for the SCHEDULE prompt in order entry. ",
      "fieldNumber_": 62.04
    },
    {
      "fieldNumber": 62.05,
      "fieldName": "CORRESPONDING OUTPATIENT DRUG",
      "dataType": "POINTER",
      "rawType": "*P50'",
      "required": false,
      "pointerTo": 50,
      "helpText": "  This is used by the Unit Dose Medications package in such things as the Authorized Absence/Discharge Orders form. ",
      "fieldNumber_": 62.05
    },
    {
      "fieldNumber": 63,
      "fieldName": "APPLICATION PACKAGES' USE",
      "dataType": "FREE-TEXT",
      "rawType": "FIa",
      "required": false,
      "helpText": "This field is free text, but contains the codes of the DHCP packages that consider this drug part of its formulary.  This field is set through the routine ^PSGIU, and NOT through VA FileMan.   NOTES: Uneditable through VA FileMan. ",
      "fieldNumber_": 63
    },
    {
      "fieldNumber": 64,
      "fieldName": "*PRIMARY DRUG",
      "dataType": "POINTER",
      "rawType": "P50.3'",
      "required": false,
      "pointerTo": 50.3,
      "helpText": "  This is the corresponding Primary Drug for this dispense drug.  A primary drug does not have a dosage associated with it. ",
      "fieldNumber_": 64
    },
    {
      "fieldNumber": 65,
      "fieldName": "FORMULARY ALTERNATIVE",
      "dataType": "POINTER",
      "rawType": "50.065P",
      "required": false,
      "helpText": "  This is a formulary alternative to this non-formulary drug.  Any formulary alternatives are shown to non-pharmacists whenever they attempt to order a non-formulary drug. ",
      "fieldNumber_": 65
    },
    {
      "fieldNumber": 66,
      "fieldName": "MAXIMUM DAYS SUPPLY",
      "dataType": "NUMERIC",
      "rawType": "NJ3,0X",
      "length": 3,
      "required": false,
      "helpText": "This field is used to determine the maximum number for days supply that may be assigned to this drug. If this field is left blank, the MAXIMUM DAYS SUPPLY is set to a default of 90 unless the drug is a controlled  substance or Clozapine. Any value greater than 90 increases the number of potential copay units above 3.    The maximum value allowed for this field is 365 (days) for most drugs,  however:   - Schedule 2 controlled substances have a 30-day maximum days supply   limit.   - Schedules 3 t",
      "fieldNumber_": 66
    },
    {
      "fieldNumber": 81,
      "fieldName": "DAW CODE",
      "dataType": "NUMERIC",
      "rawType": "NJ2,0X",
      "length": 2,
      "required": false,
      "helpText": "Dispensed As Written code. This information is used for NCPDP electronic claim transmission to third party payers (insurance companies). ",
      "fieldNumber_": 81
    },
    {
      "fieldNumber": 82,
      "fieldName": "NCPDP DISPENSE UNIT",
      "dataType": "SET",
      "rawType": "RSX",
      "required": true,
      "setOfCodes": "EA:EACH;GM:GRAMS;ML:MILLILITERS;",
      "helpText": "The NCPDP QUANTITY MULTIPLIER field and this field are used to determine metric quantity for electronic 3rd Party billing purposes.     This field indicates the NCPDP standard billing Unit of Measure (EA - EACH; GM - GRAMS; ML - MILLILITERS).   ",
      "fieldNumber_": 82
    },
    {
      "fieldNumber": 83,
      "fieldName": "NCPDP QUANTITY MULTIPLIER",
      "dataType": "NUMERIC",
      "rawType": "RNJ9,5X",
      "length": 9,
      "required": true,
      "helpText": "The NCPDP DISPENSE UNIT field and this field are used to determine  metric quantity for electronic 3rd Party billing purposes.   This field contains the number that will be multiplied by the quantity in the prescription in order to determine the correct quantity to  electronically bill 3rd party insurance companies. ",
      "fieldNumber_": 83
    },
    {
      "fieldNumber": 84,
      "fieldName": "EPHARMACY BILLABLE",
      "dataType": "SET",
      "rawType": "S",
      "required": false,
      "setOfCodes": "0:NO;1:YES;",
      "helpText": "This field indicates whether a prescription for this drug is  billable. In general, OTCs and supplies are not covered, except  insulin, glucose test strips, insulin syringes and needles.   Some plans cover preventative care OTC products.  A review of  the Payable Claims Report may help determine if a product marked as billable is covered. ",
      "fieldNumber_": 84
    },
    {
      "fieldNumber": 85,
      "fieldName": "EPHARMACY BILLABLE (TRICARE)",
      "dataType": "SET",
      "rawType": "S",
      "required": false,
      "setOfCodes": "0:NO;1:YES;",
      "helpText": "This field indicates whether a prescription for this drug is TRICARE  billable. In general, OTCs and supplies are not covered, except  insulin, glucose test strips, insulin syringes, needles and inhaler  spacers.  If unsure mark as billable and change if prescriptions  reject as not covered. ",
      "fieldNumber_": 85
    },
    {
      "fieldNumber": 86,
      "fieldName": "EPHARMACY BILLABLE (CHAMPVA)",
      "dataType": "SET",
      "rawType": "S",
      "required": false,
      "setOfCodes": "0:NO;1:YES;",
      "helpText": "This field indicates whether a prescription for this drug is CHAMPVA  billable.  In general, OTCs and supplies are not covered, except  insulin, glucose test scripts, insulin syringes, needles and inhaler spacers.  If unsure mark as billable and change if prescriptions reject as not covered. ",
      "fieldNumber_": 86
    },
    {
      "fieldNumber": 87,
      "fieldName": "SENSITIVE DIAGNOSIS DRUG",
      "dataType": "SET",
      "rawType": "S",
      "required": false,
      "setOfCodes": "0:NO;1:YES;",
      "helpText": "This field indicates whether this drug is used EXCLUSIVELY to treat one of the VA's sensitive diagnoses, HIV, drug abuse, alcohol abuse and Sickle Cell anemia. ",
      "fieldNumber_": 87
    },
    {
      "fieldNumber": 100,
      "fieldName": "INACTIVE DATE",
      "dataType": "DATE",
      "rawType": "D",
      "required": false,
      "helpText": "This is the date the drug is inactive. ",
      "fieldNumber_": 100
    },
    {
      "fieldNumber": 101,
      "fieldName": "MESSAGE",
      "dataType": "FREE-TEXT",
      "rawType": "F",
      "required": false,
      "helpText": "Message displayed whenever drug is selected for RX.  Commonly used to warn about restrictions to certain services, doctors, etc.  This is purely a passive informational free text field. ",
      "fieldNumber_": 101
    },
    {
      "fieldNumber": 102,
      "fieldName": "RESTRICTION",
      "dataType": "FREE-TEXT",
      "rawType": "F",
      "required": false,
      "helpText": "  This is any restrictions that may apply to this drug. ",
      "fieldNumber_": 102
    },
    {
      "fieldNumber": 212,
      "fieldName": "ATC CANISTER",
      "dataType": "POINTER",
      "rawType": "50.0212P",
      "required": false,
      "helpText": "  This is the ATC dispensing machine canister number(s) for this drug by ward group.  If a ward group does not have a canister number, the pick lists for the ward group will not send this drug to the ATC. ",
      "fieldNumber_": 212
    },
    {
      "fieldNumber": 212.1,
      "fieldName": "*ATC CANISTER",
      "dataType": "NUMERIC",
      "rawType": "NJ3,0",
      "length": 3,
      "required": false,
      "helpText": "  This should be the number of the canister from the Baxter ATC 212 dispensing machine that contains this drug.  If no number is entered here, the Unit Dose package will assume that this drug is NOT currently in the ATC. ",
      "fieldNumber_": 212.1
    },
    {
      "fieldNumber": 212.2,
      "fieldName": "ATC MNEMONIC",
      "dataType": "FREE-TEXT",
      "rawType": "F",
      "required": false,
      "helpText": "  This is the link between the Unit Dose package and the ATC dispensing machine.  The data here is sent to the ATC, and therefore MUST match the mnemonic entered for this same drug in the ATC.  If the mnemonic entered here does not match a mnemonic within the ATC, any pick list with this mnemonic sent to the ATC will not complete. ",
      "fieldNumber_": 212.2
    },
    {
      "fieldNumber": 213,
      "fieldName": "CMOP DISPENSE",
      "dataType": "SET",
      "rawType": "S",
      "required": false,
      "setOfCodes": "0:NO;1:YES;",
      "helpText": "Indicates if this drug may be dispensed from the Consolidated Mail Outpatient Pharmacy System. ",
      "fieldNumber_": 213
    },
    {
      "fieldNumber": 214,
      "fieldName": "ACTIVITY LOG",
      "dataType": "DATE",
      "rawType": "50.0214DA",
      "required": false,
      "helpText": "Date the activity occurred.   ",
      "isMultiple": true,
      "subFileNumber": 50.0214,
      "fieldNumber_": 214
    },
    {
      "fieldNumber": 215,
      "fieldName": "QUANTITY DISPENSE MESSAGE",
      "dataType": "FREE-TEXT",
      "rawType": "FX",
      "required": false,
      "helpText": "This is a free text description used by pharmacy personnel to indicate which quantities for the drug/item are stocked by the Outpatient Pharmacy system for this facility. ",
      "fieldNumber_": 215
    },
    {
      "fieldNumber": 300,
      "fieldName": "INPATIENT PHARMACY LOCATION",
      "dataType": "FREE-TEXT",
      "rawType": "F",
      "required": false,
      "helpText": "Enter from 1 to 3 location codes, each separated by commas, that define the location of this item in the inpatient pharmacy storage.  This will be used to sort Automatic Replenishment reports for easier location of items. ",
      "fieldNumber_": 300
    },
    {
      "fieldNumber": 301,
      "fieldName": "AR/WS AMIS CATEGORY",
      "dataType": "SET",
      "rawType": "S",
      "required": false,
      "setOfCodes": "0:Field 03 or 04 - Doses by Type;1:Field 06 or 07 - Units of Issue;2:Field 17 - Fluids and Admin Sets;3:Field 22 - Blood Products;",
      "helpText": "This refers to the category that this drug is to be classified as for AMIS  statistics in Automatic Replenishment/Ward Stock. ",
      "fieldNumber_": 301
    },
    {
      "fieldNumber": 302,
      "fieldName": "AR/WS AMIS CONVERSION NUMBER",
      "dataType": "NUMERIC",
      "rawType": "NJ4,0",
      "length": 4,
      "required": false,
      "helpText": "This number reflects the number of doses/units contained in the dispensed drug for Automatic Replenishment/Ward Stock AMIS statistics. For example:  For a 20cc vial, the quantity dispensed is 1, and               the conversion number is 20.               For 5 oz. antacid, the quantity dispensed is 1, and               the conversion number is 1.               For a bottle of 100 aspirin, the quantity dispensed is 1,               and the conversion number is 100. ",
      "fieldNumber_": 302
    },
    {
      "fieldNumber": 400,
      "fieldName": "SERVICE CODE",
      "dataType": "NUMERIC",
      "rawType": "NJ6,0",
      "length": 6,
      "required": false,
      "helpText": "The Charge Description Master (CDM) Change Control board assigns value for this field. The value should be a number between 600001-699999.  ",
      "fieldNumber_": 400
    },
    {
      "fieldNumber": 441,
      "fieldName": "IFCAP ITEM NUMBER",
      "dataType": "POINTER",
      "rawType": "50.0441P",
      "required": false,
      "helpText": "To provide a direct link between the DRUG file and the ITEM MASTER file. ",
      "fieldNumber_": 441
    },
    {
      "fieldNumber": 900,
      "fieldName": "OLD NAMES",
      "dataType": "SUBFILE",
      "rawType": "50.01A",
      "required": false,
      "isMultiple": true,
      "subFileNumber": 50.01,
      "fieldNumber_": 900
    },
    {
      "fieldNumber": 901,
      "fieldName": "STRENGTH",
      "dataType": "NUMERIC",
      "rawType": "NJ13,4X",
      "length": 13,
      "required": false,
      "helpText": "This field is a numeric value representing the single dose of medication supplied by this product. ",
      "fieldNumber_": 901
    },
    {
      "fieldNumber": 902,
      "fieldName": "UNIT",
      "dataType": "POINTER",
      "rawType": "P50.607'I",
      "required": false,
      "pointerTo": 50.607,
      "helpText": "Unit of measure. Pointer to the Drug Units File #50.607. ",
      "fieldNumber_": 902
    },
    {
      "fieldNumber": 903,
      "fieldName": "POSSIBLE DOSAGES",
      "dataType": "SUBFILE",
      "rawType": "50.0903I",
      "required": false,
      "helpText": "This multiple contains the dispense units per dose, dose and package fields. Possible Dosages can be created only for drugs that meet the specified criteria based on the VA Product File match. Possible Dosages are numeric. If a drug cannot have Possible Dosages based on the criteria not being met, then Local Possible Dosages should be created for the drug. ",
      "isMultiple": true,
      "subFileNumber": 50.0903,
      "fieldNumber_": 903
    },
    {
      "fieldNumber": 904,
      "fieldName": "LOCAL POSSIBLE DOSAGE",
      "dataType": "SUBFILE",
      "rawType": "50.0904I",
      "required": false,
      "helpText": "This multiple contains the local possible dose and package. If a drug does not have Possible Dosages because it does not meet the specified criteria based on the VA Product File match, then Local Possible Dosages should be created. ",
      "isMultiple": true,
      "subFileNumber": 50.0904,
      "fieldNumber_": 904
    },
    {
      "fieldNumber": 905,
      "fieldName": "CORRESPONDING INPATIENT DRUG",
      "dataType": "POINTER",
      "rawType": "P50'X",
      "required": false,
      "pointerTo": 50,
      "helpText": "This field will be used when transferring orders from Outpatient Pharmacy to Inpatient Medications. Only drugs marked for Inpatient Medications can be selected. ",
      "fieldNumber_": 905
    },
    {
      "fieldNumber": 906,
      "fieldName": "OPAI",
      "dataType": "POINTER",
      "rawType": "50.0906IPA",
      "required": false,
      "helpText": "This multiple contains the automated dispensing devices associated with a  division for this drug. ",
      "fieldNumber_": 906
    },
    {
      "fieldNumber": 907,
      "fieldName": "RESTRICT FOR ONEVA PHARMACY",
      "dataType": "SET",
      "rawType": "St11",
      "required": false,
      "helpText": "This flag will control if a drug can be processed using OneVA Pharmacy. A value of 1 indicates prescriptions for this drug may not be filled via OneVA Pharmacy.  A value of 0 or blank indicates prescriptions for this drug may be filled via OneVA Pharmacy. Setting this field to 1 at either the Host site or Dispensing site will prevent prescriptions for this drug from being filled via OneVA Pharmacy. ",
      "fieldNumber_": 907
    },
    {
      "fieldNumber": 608009,
      "fieldName": "MAN FINAL NODE",
      "dataType": "POINTER",
      "rawType": "50.0608009P",
      "required": false,
      "fieldNumber_": 608009
    },
    {
      "fieldNumber": 623002,
      "fieldName": "*LAB TEST MONITOR",
      "dataType": "POINTER",
      "rawType": "P60'",
      "required": false,
      "pointerTo": 60,
      "helpText": "This is the lab test results of which should be checked before this drug is dispensed. ",
      "fieldNumber_": 623002
    },
    {
      "fieldNumber": 623003,
      "fieldName": "*MONITOR MAX DAYS",
      "dataType": "NUMERIC",
      "rawType": "NJ3,0",
      "length": 3,
      "required": false,
      "helpText": "This is the number of days during which the results of the lab tests are of interest when dispensing this drug. ",
      "fieldNumber_": 623003
    },
    {
      "fieldNumber": 623004,
      "fieldName": "*SPECIMEN TYPE",
      "dataType": "POINTER",
      "rawType": "P61'",
      "required": false,
      "pointerTo": 61,
      "helpText": "This is the specimen type on which the lab test should be run. ",
      "fieldNumber_": 623004
    },
    {
      "fieldNumber": 623008,
      "fieldName": "*MONITOR ROUTINE",
      "dataType": "FREE-TEXT",
      "rawType": "F",
      "required": false,
      "helpText": "This is the name of the routine which is called to do all necessary checking on lab test results before dispensing this drug. ",
      "fieldNumber_": 623008
    }
  ],
  "fieldCount": 90,
  "crossReferences": [
    {"name": "AB", "field": },
    {"name": "AC", "field": },
    {"name": "ACLOZ", "field": },
    {"name": "AD", "field": },
    {"name": "AE", "field": },
    {"name": "AEXP", "field": },
    {"name": "AF", "field": },
    {"name": "AFA", "field": },
    {"name": "AG", "field": },
    {"name": "AH", "field": },
    {"name": "AI", "field": },
    {"name": "AIU", "field": },
    {"name": "AIUU", "field": },
    {"name": "AJ", "field": },
    {"name": "AK", "field": },
    {"name": "AND", "field": },
    {"name": "AOCC", "field": },
    {"name": "AP", "field": },
    {"name": "APC", "field": },
    {"name": "APCC", "field": },
    {"name": "APN", "field": },
    {"name": "APN1", "field": },
    {"name": "APN2", "field": },
    {"name": "APR", "field": },
    {"name": "AQ", "field": },
    {"name": "AQ1", "field": },
    {"name": "AQ2", "field": },
    {"name": "AR", "field": },
    {"name": "ASP", "field": },
    {"name": "AUDAP", "field": },
    {"name": "AVSN", "field": },
    {"name": "B", "field": },
    {"name": "C", "field": },
    {"name": "DTXT", "field": },
    {"name": "DUO", "field": },
    {"name": "IU", "field": },
    {"name": "NDC", "field": },
    {"name": "PRC", "field": },
    {"name": "VAC", "field": },
    {"name": "VAPN", "field": },
    {"name": "XATC", "field": },
    {"name": "ZATC", "field": },
    {"name": "50", "field": .01, "type": "regular"},
    {"name": "50", "field": .01, "type": "regular"},
    {"name": "50", "field": .01, "type": "regular"},
    {"name": "50", "field": .01, "type": "regular"},
    {"name": "50", "field": .01, "type": "regular"},
    {"name": "50", "field": 2, "type": "regular"},
    {"name": "50", "field": 2, "type": "regular"},
    {"name": "50", "field": 2, "type": "regular"},
    {"name": "50", "field": 2.1, "type": "regular"},
    {"name": "50", "field": 2.1, "type": "regular"},
    {"name": "50", "field": 3, "type": "regular"},
    {"name": "", "field": 13, "type": "regular"},
    {"name": "50", "field": 13, "type": "regular"},
    {"name": "", "field": 15, "type": "regular"},
    {"name": "50", "field": 15, "type": "regular"},
    {"name": "50", "field": 17.1, "type": "regular"},
    {"name": "50", "field": 17.5, "type": "regular"},
    {"name": "50", "field": 20, "type": "regular"},
    {"name": "50", "field": 20, "type": "regular"},
    {"name": "50", "field": 21, "type": "regular"},
    {"name": "50", "field": 22, "type": "regular"},
    {"name": "50", "field": 22, "type": "regular"},
    {"name": "50", "field": 25, "type": "regular"},
    {"name": "", "field": 25, "type": "regular"},
    {"name": "50", "field": 27, "type": "regular"},
    {"name": "50", "field": 28, "type": "regular"},
    {"name": "50", "field": 31, "type": "regular"},
    {"name": "50", "field": 51, "type": "regular"},
    {"name": "50", "field": 63, "type": "regular"},
    {"name": "50", "field": 63, "type": "regular"},
    {"name": "50", "field": 64, "type": "regular"},
    {"name": "50", "field": 64, "type": "regular"},
    {"name": "50", "field": 64, "type": "regular"},
    {"name": "", "field": 64, "type": "regular"},
    {"name": "", "field": 64, "type": "regular"},
    {"name": "50", "field": 100, "type": "regular"},
    {"name": "50", "field": 100, "type": "regular"},
    {"name": "50", "field": 100, "type": "regular"},
    {"name": "50", "field": 212.2, "type": "regular"},
    {"name": "50", "field": 213, "type": "regular"},
    {"name": "50", "field": 213, "type": "regular"},
    {"name": "50", "field": 901, "type": "regular"}
  ],
  "identifiers": [
    {"field": 2, "value": "W \"\""},
    {"field": 6, "value": "W \"\""},
    {"field": 25, "value": "S %I=Y,Y=$S('$D(^(\"ND\")):\"\",$D(^PS(50.605,+$P(^(\"ND\"),U,6),0))#2:$P(^(0),U,1),1:\"\"),C=$P(^DD(50.605,.01,0),U,2) D Y^DIQ:Y]\"\" W \"   \",Y,@(\"$E(\"_DIC_\"%I,0),0)\") S Y=%I K %I"},
    {"field": 51, "value": "W:$P(^(0),\"^\",9) \"   N/F\""},
    {"field": 100, "value": "W:$D(^(\"I\")) \"   \",$E($P(^(\"I\"),U,1),4,5)_\"-\"_$E($P(^(\"I\"),U,1),6,7)_\"-\"_$E($P(^(\"I\"),U,1),2,3)"},
    {"field": 101, "value": "W:$P(^(0),\"^\",10)]\"\" \"   \",$P(^(0),U,10),$C(7)"},
    {"field": 102, "value": "W:$D(^(2)) \"   \",$P(^(2),U,2)"}
  ]
}
