{
  "fileNumber": 52.52,
  "fileName": "CLOZAPINE PRESCRIPTION OVERRIDES",
  "globalRoot": "52.52D",
  "globalReference": "^PS(52.52,",
  "ddAccess": "N",
  "securityAudit": "audited",
  "fields": [
    {
      "fieldNumber": .01,
      "fieldName": "DATE TIME",
      "dataType": "DATE",
      "rawType": "MRDI",
      "required": true,
      "helpText": "This is the date and time of the decision to override the prohibition on dispensing clozaril. ",
      "fieldNumber_": .01
    },
    {
      "fieldNumber": 1,
      "fieldName": "PRESCRIPTION NUMBER",
      "dataType": "POINTER",
      "rawType": "RP52'I",
      "required": true,
      "pointerTo": 52,
      "helpText": "This is the prescription number of the clozapine prescription. ",
      "fieldNumber_": 1
    },
    {
      "fieldNumber": 2,
      "fieldName": "USER ENTERING",
      "dataType": "POINTER",
      "rawType": "RP200'I",
      "required": true,
      "pointerTo": 200,
      "helpText": "This is the user who entered the prescription. ",
      "fieldNumber_": 2
    },
    {
      "fieldNumber": 3,
      "fieldName": "APPROVING TEAM MEMBER",
      "dataType": "POINTER",
      "rawType": "RP200'I",
      "required": true,
      "pointerTo": 200,
      "helpText": "This is the member of the clozapine treatment team who authorized this prescription to be filled. ",
      "fieldNumber_": 3
    },
    {
      "fieldNumber": 4,
      "fieldName": "REASON FOR OVERRIDE",
      "dataType": "POINTER",
      "rawType": "RP52.54'",
      "required": true,
      "pointerTo": 52.54,
      "helpText": "This field records the reason as a pointer to file #52.54. ",
      "fieldNumber_": 4
    },
    {
      "fieldNumber": 5,
      "fieldName": "COMMENTS",
      "dataType": "FREE-TEXT",
      "rawType": "RFIX",
      "required": true,
      "helpText": "This is any information about why the prescription was filled. ",
      "fieldNumber_": 5
    },
    {
      "fieldNumber": 6,
      "fieldName": "SECOND APPROVING TEAM MEMBER",
      "dataType": "POINTER",
      "rawType": "RP200'",
      "required": true,
      "pointerTo": 200,
      "helpText": "This field records the name as a pointer to file 200). ",
      "fieldNumber_": 6
    },
    {
      "fieldNumber": 7,
      "fieldName": "OVERRIDE TEAM MEMBER",
      "dataType": "POINTER",
      "rawType": "P200'I",
      "required": false,
      "pointerTo": 200,
      "helpText": "This is the member of the clozapine team who was selected to verify an  override for this prescription or order. ",
      "fieldNumber_": 7
    },
    {
      "fieldNumber": 8,
      "fieldName": "OVERRIDE PROVIDER",
      "dataType": "POINTER",
      "rawType": "P200'I",
      "required": false,
      "pointerTo": 200,
      "helpText": "This the provider who made the override for the prescription or order. ",
      "fieldNumber_": 8
    },
    {
      "fieldNumber": 9,
      "fieldName": "ORDER",
      "dataType": "POINTER",
      "rawType": "P100'I",
      "required": false,
      "pointerTo": 100,
      "helpText": "This is the clozapine order number associated with this override. ",
      "fieldNumber_": 9
    }
  ],
  "fieldCount": 10,
  "crossReferences": [
    {"name": "A", "field": },
    {"name": "B", "field": },
    {"name": "52.52", "field": .01, "type": "regular"},
    {"name": "52.52", "field": 1, "type": "regular"}
  ],
  "identifiers": [

  ]
}
