{
  "fileNumber": 9002313.93,
  "fileName": "BPS NCPDP REJECT CODES",
  "globalRoot": "9002313.93",
  "globalReference": "^BPSF(9002313.93,",
  "ddAccess": "N",
  "securityAudit": "audited",
  "fields": [
    {
      "fieldNumber": .01,
      "fieldName": "CODE",
      "dataType": "FREE-TEXT",
      "rawType": "RFJ3",
      "length": 3,
      "required": true,
      "helpText": "Reject Code returned by the payer for the reason of the rejection.  This is based on the NCPDP standards. ",
      "fieldNumber_": .01
    },
    {
      "fieldNumber": .02,
      "fieldName": "EXPLANATION",
      "dataType": "FREE-TEXT",
      "rawType": "FJ70",
      "length": 70,
      "required": false,
      "helpText": "Textual explanation of the claim rejection. ",
      "fieldNumber_": .02
    }
  ],
  "fieldCount": 2,
  "crossReferences": [
    {"name": "B", "field": },
    {"name": "9002313.93", "field": .01, "type": "regular"}
  ],
  "identifiers": [
    {"field": .02, "value": "W \"   \",$P(^(0),U,2)"}
  ]
}
